lads_opcua_viewer/__init__.py
lads_opcua_viewer/cli.py
lads_opcua_viewer/main.py
lads_opcua_viewer-0.1.0.dist-info/METADATA
lads_opcua_viewer-0.1.0.dist-info/WHEEL
lads_opcua_viewer-0.1.0.dist-info/entry_points.txt
lads_opcua_viewer-0.1.0.dist-info/licenses/LICENSE
lads_opcua_viewer-0.1.0.dist-info/RECORD
